old_fashioned_nlp/__init__.py
old_fashioned_nlp/metrics.py
old_fashioned_nlp/classification/__init__.py
old_fashioned_nlp/classification/sklearn_classifiers.py
old_fashioned_nlp/preprocessing/__init__.py
old_fashioned_nlp/preprocessing/clean.py
old_fashioned_nlp/regression/__init__.py
old_fashioned_nlp/regression/sklearn_regressors.py
old_fashioned_nlp/tagging/__init__.py
old_fashioned_nlp/tagging/token.py
old_fashioned_nlp-0.1.3.dist-info/LICENSE
old_fashioned_nlp-0.1.3.dist-info/METADATA
old_fashioned_nlp-0.1.3.dist-info/WHEEL
old_fashioned_nlp-0.1.3.dist-info/top_level.txt
old_fashioned_nlp-0.1.3.dist-info/RECORD
