Metadata-Version: 2.1
Name: old-fashioned-nlp
Version: 0.1.3
Summary: Sklearn base nlp models
Home-page: https://github.com/sleeplessindebugging/old-fashioned-nlp
Author: Chenghao Mou
Author-email: mouchenghao@gmail.com
License: UNKNOWN
Platform: UNKNOWN
Classifier: Programming Language :: Python :: 3
Classifier: License :: OSI Approved :: MIT License
Classifier: Operating System :: OS Independent
Requires-Python: >=3.6
Requires-Dist: nlp
Requires-Dist: pytest
Requires-Dist: nltk
Requires-Dist: scipy
Requires-Dist: numpy
Requires-Dist: loguru
Requires-Dist: sklearn-crfsuite
Requires-Dist: pandas
Requires-Dist: regex
Requires-Dist: rich
Requires-Dist: scikit-learn
